omron_connect_api/__init__.py
omron_connect_api/omron_connect_api.py
omron_connect_api/omron_connect_api_errors.py
omron_connect_api/blood_pressure/__init__.py
omron_connect_api/blood_pressure/blood_pressure_reading.py
omron_connect_api/blood_pressure/blood_pressure_reading_response.py
omron_connect_api-0.1.1.dist-info/METADATA
omron_connect_api-0.1.1.dist-info/WHEEL
omron_connect_api-0.1.1.dist-info/licenses/LICENSE
omron_connect_api-0.1.1.dist-info/RECORD
