Metadata-Version: 2.4
Name: omron-connect-api
Version: 0.1.1
Summary: Library to communicate with OMRON connect API
Project-URL: Homepage, https://github.com/happydev-ca/omron-connect-api
Project-URL: Issues, https://github.com/happydev-ca/omron-connect-api/issues
Author-email: Francois Perron <fperron@gmail.com>
License-File: LICENSE
Classifier: Development Status :: 4 - Beta
Classifier: License :: OSI Approved :: MIT License
Classifier: Operating System :: OS Independent
Classifier: Programming Language :: Python :: 3
Classifier: Topic :: Home Automation
Requires-Python: >=3.13
Requires-Dist: aiohttp
